hpe_opsramp_cli/__init__.py
hpe_opsramp_cli/cli_logger.py
hpe_opsramp_cli/cli_utils.py
hpe_opsramp_cli/main.py
hpe_opsramp_cli/opsql.json
hpe_opsramp_cli/opsramp_environment.py
hpe_opsramp_cli/otel_logger.py
hpe_opsramp_cli/post_opsql.py
hpe_opsramp_cli/progress_bar.py
hpe_opsramp_cli/settings.py
hpe_opsramp_cli/singleton_logger.py
hpe_opsramp_cli/unmanage_alert_resources.py
hpe_opsramp_cli/unmanage_alert_resources_opsql.json
hpe_opsramp_cli/version.py
hpe_opsramp_cli-1.0.0.dist-info/METADATA
hpe_opsramp_cli-1.0.0.dist-info/WHEEL
hpe_opsramp_cli-1.0.0.dist-info/entry_points.txt
hpe_opsramp_cli-1.0.0.dist-info/RECORD
