Metadata-Version: 2.4
Name: hpe-opsramp-cli
Version: 1.0.0
Summary: OpsRamp CLI is a command line utility for the HPE OpsRamp SaaS platform
Author-email: BalaSubramanian-Vetrivel <balasubramanian.vetrivel@hpe.com>
Requires-Python: >=3.12
Requires-Dist: opentelemetry-api>=1.31.0
Requires-Dist: opentelemetry-exporter-jaeger>=1.21.0
Requires-Dist: opentelemetry-exporter-otlp>=1.31.0
Requires-Dist: opentelemetry-instrumentation-logging>=0.52b0
Requires-Dist: opentelemetry-instrumentation-requests>=0.52b0
Requires-Dist: opentelemetry-sdk>=1.31.0
Requires-Dist: pytest>=8.3.4
Requires-Dist: pyyaml==6.0.2
Requires-Dist: requests>=2.32.3
Requires-Dist: rich==13.9.4
Requires-Dist: typer>=0.15.2
Requires-Dist: types-pyyaml>=6.0.12.20241230
Requires-Dist: types-requests>=2.32.0.20250306
Requires-Dist: typing-extensions==4.12.2
